qasm2image/__init__.py
qasm2image/qasm2pdf.py
qasm2image/qasm2png.py
qasm2image/qasm2ps.py
qasm2image/qasm2svg.py
qasm2image/svg/__init__.py
qasm2image/svg/_constants.py
qasm2image/svg/_drawing.py
qasm2image/svg/_helpers.py
qasm2image-0.7.0.dist-info/DESCRIPTION.rst
qasm2image-0.7.0.dist-info/METADATA
qasm2image-0.7.0.dist-info/RECORD
qasm2image-0.7.0.dist-info/WHEEL
qasm2image-0.7.0.dist-info/entry_points.txt
qasm2image-0.7.0.dist-info/metadata.json
qasm2image-0.7.0.dist-info/top_level.txt
tools/__init__.py
tools/qasm2image_script.py
