Metadata-Version: 2.0
Name: qasm2image
Version: 0.7.0
Summary: An OpenQASM visualisation tool
Home-page: https://github.com/nelimeee/qasm2image
Author: Adrien Suau
Author-email: adrien.suau@grenoble-inp.org
License: UNKNOWN
Project-URL: Bug Reports, https://github.com/nelimeee/qasm2image/issues
Project-URL: Source, https://github.com/nelimeee/qasm2image
Keywords: qasm svg png visualisation
Platform: UNKNOWN
Classifier: Development Status :: 4 - Beta
Classifier: Environment :: Console
Classifier: Intended Audience :: Developers
Classifier: Intended Audience :: Science/Research
Classifier: License :: CeCILL-B Free Software License Agreement (CECILL-B)
Classifier: Programming Language :: Python :: 3 :: Only
Classifier: Topic :: Multimedia :: Graphics :: Graphics Conversion
Requires-Python: >=3.5
Requires-Dist: cairosvg
Requires-Dist: cairocffi
Requires-Dist: qiskit (>=0.5)
Requires-Dist: svgwrite
